mailwizard/__init__.py
mailwizard/core.py
mailwizard-0.1.1.dist-info/licenses/LICENSE
mailwizard-0.1.1.dist-info/METADATA
mailwizard-0.1.1.dist-info/WHEEL
mailwizard-0.1.1.dist-info/top_level.txt
mailwizard-0.1.1.dist-info/RECORD
